LICENSE
eventy/__init__.py
eventy/config/__init__.py
eventy/config/aiohttp/__init__.py
eventy/config/celery/__init__.py
eventy/config/django/__init__.py
eventy/config/sanic/__init__.py
eventy/integration/__init__.py
eventy/integration/_utils.py
eventy/integration/aiohttp.py
eventy/integration/celery.py
eventy/integration/django.py
eventy/integration/gunicorn.py
eventy/integration/requests.py
eventy/integration/sanic.py
eventy/logging/__init__.py
eventy/logging/gke_handler.py
eventy/logging/info_providers.py
eventy/logging/simple_handler.py
eventy/messaging/__init__.py
eventy/messaging/agent.py
eventy/messaging/app.py
eventy/messaging/confluent_kafka.py
eventy/messaging/errors.py
eventy/messaging/memory.py
eventy/messaging/service.py
eventy/messaging/store.py
eventy/py.typed
eventy/record/__init__.py
eventy/record/errors.py
eventy/record/event.py
eventy/record/record.py
eventy/record/request.py
eventy/record/response.py
eventy/serialization/__init__.py
eventy/serialization/avro.py
eventy/serialization/dummy.py
eventy/serialization/errors.py
eventy/serialization/json.py
eventy/trace_id/__init__.py
eventy/trace_id/context_vars.py
eventy/trace_id/generator.py
eventy/trace_id/local.py
eventy-3.4.0.dist-info/LICENSE
eventy-3.4.0.dist-info/METADATA
eventy-3.4.0.dist-info/WHEEL
eventy-3.4.0.dist-info/RECORD
