Metadata-Version: 2.1
Name: eventy
Version: 3.4.0
Summary: Qotto/eventy
Home-page: https://gitlab.com/qotto/oss/eventy
License: MIT
Author: Qotto Dev Team
Author-email: dev@qotto.net
Requires-Python: >=3.8
Classifier: Development Status :: 3 - Alpha
Classifier: Intended Audience :: Developers
Classifier: License :: OSI Approved :: MIT License
Classifier: Programming Language :: Python :: 3
Classifier: Programming Language :: Python :: 3.8
Classifier: Programming Language :: Python :: 3.9
Classifier: Programming Language :: Python :: 3.10
Classifier: Programming Language :: Python :: 3.11
Classifier: Programming Language :: Python :: 3.7
Provides-Extra: aiohttp
Provides-Extra: avro
Provides-Extra: celery
Provides-Extra: confluent-kafka
Provides-Extra: django
Provides-Extra: gunicorn
Provides-Extra: requests
Provides-Extra: sanic
Requires-Dist: PyYAML (>=5) ; extra == "avro"
Requires-Dist: aiohttp (>=1) ; extra == "aiohttp"
Requires-Dist: avro-python3 (>=1.10) ; extra == "avro"
Requires-Dist: celery (>=5) ; extra == "celery"
Requires-Dist: coloredlogs (>=15)
Requires-Dist: confluent-kafka (>=1.7) ; extra == "confluent-kafka"
Requires-Dist: contextvars (>=2)
Requires-Dist: django (>=1) ; extra == "django"
Requires-Dist: gunicorn (>=20) ; extra == "gunicorn"
Requires-Dist: requests (>=2) ; extra == "requests"
Requires-Dist: sanic (>=18) ; extra == "sanic"
Requires-Dist: semver (>=2)
Project-URL: Bug Reports, https://gitlab.com/qotto/oss/eventy/-/issues
Project-URL: Documentation, https://qotto.gitlab.io/oss/eventy
Project-URL: Qotto, http://www.qotto.net
Project-URL: Repository, https://gitlab.com/qotto/oss/eventy
Project-URL: Source, https://gitlab.com/qotto/oss/eventy
